src/__init__.py
src/pambas1.py
pambas1-0.2.dist-info/METADATA
pambas1-0.2.dist-info/WHEEL
pambas1-0.2.dist-info/top_level.txt
pambas1-0.2.dist-info/RECORD
