Metadata-Version: 2.1
Name: pambas1
Version: 0.2
Summary: UNKNOWN
Home-page: UNKNOWN
License: UNKNOWN
Platform: UNKNOWN
Requires-Dist: pyperclip
Requires-Dist: g4f
